Workbook

Sheet Dashboard
B2: Castellan BESS — Behind-the-Meter Storage Model
B3: Account 200027805928 · Ontario GS >50 kW · built from interval data + 22 months of bills
B5: THE SITUATION
B6: • Winter-heating load: peaks ~115–120 kW in winter, <25 kW summer (load factor 22%).
B7: • Bill dominated by a demand charge ~$25.8/kW-month — each kW of peak ≈ $310/yr.
B8: • A battery saves almost entirely by shaving the winter peak (flat energy rate → little arbitrage).
B9: • Peaks are long plateaus (6–72 h) so the battery is energy-limited: duration matters, not power.
B11: HEADLINE — value pick 50 kW / 150 kWh (live)
B12: Yr-1 total benefit | E12: ='Sizing Comparison'!H7
B13: Net capex (after ITC) | E13: ='Sizing Comparison'!K7
B14: Simple payback | E14: ='Sizing Comparison'!L7
B15: 15-yr NPV @ discount | E15: ='Sizing Comparison'!M7
B16: IRR | E16: ='Sizing Comparison'!N7
B18: HOW TO USE
B19: Assumptions | C19: Edit yellow cells — tariff, battery, capex, ITC, value streams. All else recalcs.
B20: Sizing Comparison | C20: 9 sizes: benefit, capex, payback, NPV, IRR. Green = recommended.
B21: Bill Impact | C21: Month-by-month bill before vs after.
B22: Dispatch | C22: Hour-by-hour of what the battery does on a cold week + state of charge.
B23: Cash Flow | C23: 15-yr cash flow for two sizes with payback / NPV / IRR.
B24: Backup Resilience | C24: Outage runtime by season.
B25: Sensitivity | C25: Payback heat-map vs demand charge and battery cost.
B27: ⚠ Confirm the $25.84/kW demand charge (kW vs 15-min kVA) against the real tariff — it drives the whole result.

Sheet Assumptions
A1: Castellan BESS — Assumptions (edit the YELLOW cells; everything recalculates)
A3: TARIFF (derived from 22 bills, R²=0.9994)
A4: Energy rate ($/kWh) | B4: 0.1109 | C4: Blended commodity + delivery
A5: Demand charge ($/kW-month) | B5: 25.84 | C5: ⚠ CONFIRM vs tariff — drives everything
A6: Fixed monthly charge ($) | B6: 137 | C6: Not affected by BESS
A7: Demand-rate escalation (%/yr) | B7: 0.025 | C7: Utility inflation
A8: TOU energy spread on-vs-off ($/kWh) | B8: 0 | C8: Set >0 if on TOU/ULO to value arbitrage
A9: Arbitrage cycles per year | B9: 250 | C9: Full charge/discharge cycles for arbitrage
A11: BATTERY / TECH
A12: Round-trip efficiency | B12: 0.9
A13: Usable depth of discharge | B13: 0.8 | C13: SOC 10–90%
A14: Capacity degradation (%/yr) | B14: 0.025 | C14: Lowers savings over time
A16: CAPEX (installed, CAD)
A17: Power cost ($/kW) | B17: 400 | C17: Inverter / PCS
A18: Energy cost ($/kWh) | B18: 500 | C18: Battery modules — set 0 to test
A19: Fixed install / BOS ($) | B19: 20000 | C19: EPC, interconnect, controls
A20: Clean-Tech ITC (%) | B20: 0.3 | C20: Federal refundable credit
A22: OPERATING / FINANCE (model horizon = 15 yrs)
A23: O&M (% of capex / yr) | B23: 0.015
A24: O&M inflation (%/yr) | B24: 0.02
A25: Discount rate (%) | B25: 0.08 | C25: For NPV
A26: Resilience / backup value ($/yr) | B26: 0 | C26: Optional $ you assign to outage protection

Sheet Sizing Comparison
A1: Battery Sizing Comparison — all formulas live off the Assumptions tab
A2: Annual benefit = demand savings (kW shaved × demand rate) + arbitrage + resilience value.
A4: Power (kW) | B4: Energy (kWh) | C4: Dur (h) | D4: kW-mo shaved/yr | E4: Demand savings $ | F4: Arbitrage $/yr | G4: Resilience $/yr | H4: Yr-1 total benefit $ | I4: Capex $ | J4: ITC $ | K4: Net capex $ | L4: Payback (yr) | M4: 15-yr NPV $ | N4: IRR
A5: 30 | B5: 60 | C5: =B5/A5 | D5: 153.9 | E5: =D5*Assumptions!$B$5 | F5: =B5*Assumptions!$B$13*Assumptions!$B$8*Assumptions!$B$9*Assumptions!$B$12 | G5: =Assumptions!$B$26 | H5: =E5+F5+G5 | I5: =A5*Assumptions!$B$17+B5*Assumptions!$B$18+Assumptions!$B$19 | J5: =I5*Assumptions!$B$20 | K5: =I5-J5 | L5: =K5/H5 | M5: ='CF_Calc'!U5 | N5: ='CF_Calc'!V5
A6: 50 | B6: 100 | C6: =B6/A6 | D6: 199.7 | E6: =D6*Assumptions!$B$5 | F6: =B6*Assumptions!$B$13*Assumptions!$B$8*Assumptions!$B$9*Assumptions!$B$12 | G6: =Assumptions!$B$26 | H6: =E6+F6+G6 | I6: =A6*Assumptions!$B$17+B6*Assumptions!$B$18+Assumptions!$B$19 | J6: =I6*Assumptions!$B$20 | K6: =I6-J6 | L6: =K6/H6 | M6: ='CF_Calc'!U6 | N6: ='CF_Calc'!V6
A7: 50 | B7: 150 | C7: =B7/A7 | D7: 238.7 | E7: =D7*Assumptions!$B$5 | F7: =B7*Assumptions!$B$13*Assumptions!$B$8*Assumptions!$B$9*Assumptions!$B$12 | G7: =Assumptions!$B$26 | H7: =E7+F7+G7 | I7: =A7*Assumptions!$B$17+B7*Assumptions!$B$18+Assumptions!$B$19 | J7: =I7*Assumptions!$B$20 | K7: =I7-J7 | L7: =K7/H7 | M7: ='CF_Calc'!U7 | N7: ='CF_Calc'!V7
A8: 75 | B8: 150 | C8: =B8/A8 | D8: 238.7 | E8: =D8*Assumptions!$B$5 | F8: =B8*Assumptions!$B$13*Assumptions!$B$8*Assumptions!$B$9*Assumptions!$B$12 | G8: =Assumptions!$B$26 | H8: =E8+F8+G8 | I8: =A8*Assumptions!$B$17+B8*Assumptions!$B$18+Assumptions!$B$19 | J8: =I8*Assumptions!$B$20 | K8: =I8-J8 | L8: =K8/H8 | M8: ='CF_Calc'!U8 | N8: ='CF_Calc'!V8
A9: 100 | B9: 200 | C9: =B9/A9 | D9: 261 | E9: =D9*Assumptions!$B$5 | F9: =B9*Assumptions!$B$13*Assumptions!$B$8*Assumptions!$B$9*Assumptions!$B$12 | G9: =Assumptions!$B$26 | H9: =E9+F9+G9 | I9: =A9*Assumptions!$B$17+B9*Assumptions!$B$18+Assumptions!$B$19 | J9: =I9*Assumptions!$B$20 | K9: =I9-J9 | L9: =K9/H9 | M9: ='CF_Calc'!U9 | N9: ='CF_Calc'!V9
A10: 100 | B10: 300 | C10: =B10/A10 | D10: 285.8 | E10: =D10*Assumptions!$B$5 | F10: =B10*Assumptions!$B$13*Assumptions!$B$8*Assumptions!$B$9*Assumptions!$B$12 | G10: =Assumptions!$B$26 | H10: =E10+F10+G10 | I10: =A10*Assumptions!$B$17+B10*Assumptions!$B$18+Assumptions!$B$19 | J10: =I10*Assumptions!$B$20 | K10: =I10-J10 | L10: =K10/H10 | M10: ='CF_Calc'!U10 | N10: ='CF_Calc'!V10
A11: 100 | B11: 400 | C11: =B11/A11 | D11: 301.2 | E11: =D11*Assumptions!$B$5 | F11: =B11*Assumptions!$B$13*Assumptions!$B$8*Assumptions!$B$9*Assumptions!$B$12 | G11: =Assumptions!$B$26 | H11: =E11+F11+G11 | I11: =A11*Assumptions!$B$17+B11*Assumptions!$B$18+Assumptions!$B$19 | J11: =I11*Assumptions!$B$20 | K11: =I11-J11 | L11: =K11/H11 | M11: ='CF_Calc'!U11 | N11: ='CF_Calc'!V11
A12: 150 | B12: 300 | C12: =B12/A12 | D12: 285.8 | E12: =D12*Assumptions!$B$5 | F12: =B12*Assumptions!$B$13*Assumptions!$B$8*Assumptions!$B$9*Assumptions!$B$12 | G12: =Assumptions!$B$26 | H12: =E12+F12+G12 | I12: =A12*Assumptions!$B$17+B12*Assumptions!$B$18+Assumptions!$B$19 | J12: =I12*Assumptions!$B$20 | K12: =I12-J12 | L12: =K12/H12 | M12: ='CF_Calc'!U12 | N12: ='CF_Calc'!V12
A13: 200 | B13: 400 | C13: =B13/A13 | D13: 301.2 | E13: =D13*Assumptions!$B$5 | F13: =B13*Assumptions!$B$13*Assumptions!$B$8*Assumptions!$B$9*Assumptions!$B$12 | G13: =Assumptions!$B$26 | H13: =E13+F13+G13 | I13: =A13*Assumptions!$B$17+B13*Assumptions!$B$18+Assumptions!$B$19 | J13: =I13*Assumptions!$B$20 | K13: =I13-J13 | L13: =K13/H13 | M13: ='CF_Calc'!U13 | N13: ='CF_Calc'!V13
A15: Green = value pick. Change Energy cost to 0 on Assumptions and watch Capex/Payback/NPV/IRR all move.

Sheet CF_Calc
A1: Cash-flow engine (15 yrs) — feeds NPV/IRR on Sizing Comparison. Live.
A4: size | B4: net | C4: benefit | D4: capex | E4: Y0 | F4: Y1 | G4: Y2 | H4: Y3 | I4: Y4 | J4: Y5 | K4: Y6 | L4: Y7 | M4: Y8 | N4: Y9 | O4: Y10 | P4: Y11 | Q4: Y12 | R4: Y13 | S4: Y14 | T4: Y15 | U4: NPV | V4: IRR
A5: 30/60 | B5: ='Sizing Comparison'!K5 | C5: ='Sizing Comparison'!H5 | D5: ='Sizing Comparison'!I5 | E5: =-B5 | F5: =C5*(1+Assumptions!$B$7)^0*(1-Assumptions!$B$14*0)-D5*Assumptions!$B$23*(1+Assumptions!$B$24)^0 | G5: =C5*(1+Assumptions!$B$7)^1*(1-Assumptions!$B$14*1)-D5*Assumptions!$B$23*(1+Assumptions!$B$24)^1 | H5: =C5*(1+Assumptions!$B$7)^2*(1-Assumptions!$B$14*2)-D5*Assumptions!$B$23*(1+Assumptions!$B$24)^2 | I5: =C5*(1+Assumptions!$B$7)^3*(1-Assumptions!$B$14*3)-D5*Assumptions!$B$23*(1+Assumptions!$B$24)^3 | J5: =C5*(1+Assumptions!$B$7)^4*(1-Assumptions!$B$14*4)-D5*Assumptions!$B$23*(1+Assumptions!$B$24)^4 | K5: =C5*(1+Assumptions!$B$7)^5*(1-Assumptions!$B$14*5)-D5*Assumptions!$B$23*(1+Assumptions!$B$24)^5 | L5: =C5*(1+Assumptions!$B$7)^6*(1-Assumptions!$B$14*6)-D5*Assumptions!$B$23*(1+Assumptions!$B$24)^6 | M5: =C5*(1+Assumptions!$B$7)^7*(1-Assumptions!$B$14*7)-D5*Assumptions!$B$23*(1+Assumptions!$B$24)^7 | N5: =C5*(1+Assumptions!$B$7)^8*(1-Assumptions!$B$14*8)-D5*Assumptions!$B$23*(1+Assumptions!$B$24)^8 | O5: =C5*(1+Assumptions!$B$7)^9*(1-Assumptions!$B$14*9)-D5*Assumptions!$B$23*(1+Assumptions!$B$24)^9 | P5: =C5*(1+Assumptions!$B$7)^10*(1-Assumptions!$B$14*10)-D5*Assumptions!$B$23*(1+Assumptions!$B$24)^10 | Q5: =C5*(1+Assumptions!$B$7)^11*(1-Assumptions!$B$14*11)-D5*Assumptions!$B$23*(1+Assumptions!$B$24)^11 | R5: =C5*(1+Assumptions!$B$7)^12*(1-Assumptions!$B$14*12)-D5*Assumptions!$B$23*(1+Assumptions!$B$24)^12 | S5: =C5*(1+Assumptions!$B$7)^13*(1-Assumptions!$B$14*13)-D5*Assumptions!$B$23*(1+Assumptions!$B$24)^13 | T5: =C5*(1+Assumptions!$B$7)^14*(1-Assumptions!$B$14*14)-D5*Assumptions!$B$23*(1+Assumptions!$B$24)^14 | U5: =NPV(Assumptions!$B$25,F5:T5)+E5 | V5: =IFERROR(IRR(E5:T5),"-")
A6: 50/100 | B6: ='Sizing Comparison'!K6 | C6: ='Sizing Comparison'!H6 | D6: ='Sizing Comparison'!I6 | E6: =-B6 | F6: =C6*(1+Assumptions!$B$7)^0*(1-Assumptions!$B$14*0)-D6*Assumptions!$B$23*(1+Assumptions!$B$24)^0 | G6: =C6*(1+Assumptions!$B$7)^1*(1-Assumptions!$B$14*1)-D6*Assumptions!$B$23*(1+Assumptions!$B$24)^1 | H6: =C6*(1+Assumptions!$B$7)^2*(1-Assumptions!$B$14*2)-D6*Assumptions!$B$23*(1+Assumptions!$B$24)^2 | I6: =C6*(1+Assumptions!$B$7)^3*(1-Assumptions!$B$14*3)-D6*Assumptions!$B$23*(1+Assumptions!$B$24)^3 | J6: =C6*(1+Assumptions!$B$7)^4*(1-Assumptions!$B$14*4)-D6*Assumptions!$B$23*(1+Assumptions!$B$24)^4 | K6: =C6*(1+Assumptions!$B$7)^5*(1-Assumptions!$B$14*5)-D6*Assumptions!$B$23*(1+Assumptions!$B$24)^5 | L6: =C6*(1+Assumptions!$B$7)^6*(1-Assumptions!$B$14*6)-D6*Assumptions!$B$23*(1+Assumptions!$B$24)^6 | M6: =C6*(1+Assumptions!$B$7)^7*(1-Assumptions!$B$14*7)-D6*Assumptions!$B$23*(1+Assumptions!$B$24)^7 | N6: =C6*(1+Assumptions!$B$7)^8*(1-Assumptions!$B$14*8)-D6*Assumptions!$B$23*(1+Assumptions!$B$24)^8 | O6: =C6*(1+Assumptions!$B$7)^9*(1-Assumptions!$B$14*9)-D6*Assumptions!$B$23*(1+Assumptions!$B$24)^9 | P6: =C6*(1+Assumptions!$B$7)^10*(1-Assumptions!$B$14*10)-D6*Assumptions!$B$23*(1+Assumptions!$B$24)^10 | Q6: =C6*(1+Assumptions!$B$7)^11*(1-Assumptions!$B$14*11)-D6*Assumptions!$B$23*(1+Assumptions!$B$24)^11 | R6: =C6*(1+Assumptions!$B$7)^12*(1-Assumptions!$B$14*12)-D6*Assumptions!$B$23*(1+Assumptions!$B$24)^12 | S6: =C6*(1+Assumptions!$B$7)^13*(1-Assumptions!$B$14*13)-D6*Assumptions!$B$23*(1+Assumptions!$B$24)^13 | T6: =C6*(1+Assumptions!$B$7)^14*(1-Assumptions!$B$14*14)-D6*Assumptions!$B$23*(1+Assumptions!$B$24)^14 | U6: =NPV(Assumptions!$B$25,F6:T6)+E6 | V6: =IFERROR(IRR(E6:T6),"-")
A7: 50/150 | B7: ='Sizing Comparison'!K7 | C7: ='Sizing Comparison'!H7 | D7: ='Sizing Comparison'!I7 | E7: =-B7 | F7: =C7*(1+Assumptions!$B$7)^0*(1-Assumptions!$B$14*0)-D7*Assumptions!$B$23*(1+Assumptions!$B$24)^0 | G7: =C7*(1+Assumptions!$B$7)^1*(1-Assumptions!$B$14*1)-D7*Assumptions!$B$23*(1+Assumptions!$B$24)^1 | H7: =C7*(1+Assumptions!$B$7)^2*(1-Assumptions!$B$14*2)-D7*Assumptions!$B$23*(1+Assumptions!$B$24)^2 | I7: =C7*(1+Assumptions!$B$7)^3*(1-Assumptions!$B$14*3)-D7*Assumptions!$B$23*(1+Assumptions!$B$24)^3 | J7: =C7*(1+Assumptions!$B$7)^4*(1-Assumptions!$B$14*4)-D7*Assumptions!$B$23*(1+Assumptions!$B$24)^4 | K7: =C7*(1+Assumptions!$B$7)^5*(1-Assumptions!$B$14*5)-D7*Assumptions!$B$23*(1+Assumptions!$B$24)^5 | L7: =C7*(1+Assumptions!$B$7)^6*(1-Assumptions!$B$14*6)-D7*Assumptions!$B$23*(1+Assumptions!$B$24)^6 | M7: =C7*(1+Assumptions!$B$7)^7*(1-Assumptions!$B$14*7)-D7*Assumptions!$B$23*(1+Assumptions!$B$24)^7 | N7: =C7*(1+Assumptions!$B$7)^8*(1-Assumptions!$B$14*8)-D7*Assumptions!$B$23*(1+Assumptions!$B$24)^8 | O7: =C7*(1+Assumptions!$B$7)^9*(1-Assumptions!$B$14*9)-D7*Assumptions!$B$23*(1+Assumptions!$B$24)^9 | P7: =C7*(1+Assumptions!$B$7)^10*(1-Assumptions!$B$14*10)-D7*Assumptions!$B$23*(1+Assumptions!$B$24)^10 | Q7: =C7*(1+Assumptions!$B$7)^11*(1-Assumptions!$B$14*11)-D7*Assumptions!$B$23*(1+Assumptions!$B$24)^11 | R7: =C7*(1+Assumptions!$B$7)^12*(1-Assumptions!$B$14*12)-D7*Assumptions!$B$23*(1+Assumptions!$B$24)^12 | S7: =C7*(1+Assumptions!$B$7)^13*(1-Assumptions!$B$14*13)-D7*Assumptions!$B$23*(1+Assumptions!$B$24)^13 | T7: =C7*(1+Assumptions!$B$7)^14*(1-Assumptions!$B$14*14)-D7*Assumptions!$B$23*(1+Assumptions!$B$24)^14 | U7: =NPV(Assumptions!$B$25,F7:T7)+E7 | V7: =IFERROR(IRR(E7:T7),"-")
A8: 75/150 | B8: ='Sizing Comparison'!K8 | C8: ='Sizing Comparison'!H8 | D8: ='Sizing Comparison'!I8 | E8: =-B8 | F8: =C8*(1+Assumptions!$B$7)^0*(1-Assumptions!$B$14*0)-D8*Assumptions!$B$23*(1+Assumptions!$B$24)^0 | G8: =C8*(1+Assumptions!$B$7)^1*(1-Assumptions!$B$14*1)-D8*Assumptions!$B$23*(1+Assumptions!$B$24)^1 | H8: =C8*(1+Assumptions!$B$7)^2*(1-Assumptions!$B$14*2)-D8*Assumptions!$B$23*(1+Assumptions!$B$24)^2 | I8: =C8*(1+Assumptions!$B$7)^3*(1-Assumptions!$B$14*3)-D8*Assumptions!$B$23*(1+Assumptions!$B$24)^3 | J8: =C8*(1+Assumptions!$B$7)^4*(1-Assumptions!$B$14*4)-D8*Assumptions!$B$23*(1+Assumptions!$B$24)^4 | K8: =C8*(1+Assumptions!$B$7)^5*(1-Assumptions!$B$14*5)-D8*Assumptions!$B$23*(1+Assumptions!$B$24)^5 | L8: =C8*(1+Assumptions!$B$7)^6*(1-Assumptions!$B$14*6)-D8*Assumptions!$B$23*(1+Assumptions!$B$24)^6 | M8: =C8*(1+Assumptions!$B$7)^7*(1-Assumptions!$B$14*7)-D8*Assumptions!$B$23*(1+Assumptions!$B$24)^7 | N8: =C8*(1+Assumptions!$B$7)^8*(1-Assumptions!$B$14*8)-D8*Assumptions!$B$23*(1+Assumptions!$B$24)^8 | O8: =C8*(1+Assumptions!$B$7)^9*(1-Assumptions!$B$14*9)-D8*Assumptions!$B$23*(1+Assumptions!$B$24)^9 | P8: =C8*(1+Assumptions!$B$7)^10*(1-Assumptions!$B$14*10)-D8*Assumptions!$B$23*(1+Assumptions!$B$24)^10 | Q8: =C8*(1+Assumptions!$B$7)^11*(1-Assumptions!$B$14*11)-D8*Assumptions!$B$23*(1+Assumptions!$B$24)^11 | R8: =C8*(1+Assumptions!$B$7)^12*(1-Assumptions!$B$14*12)-D8*Assumptions!$B$23*(1+Assumptions!$B$24)^12 | S8: =C8*(1+Assumptions!$B$7)^13*(1-Assumptions!$B$14*13)-D8*Assumptions!$B$23*(1+Assumptions!$B$24)^13 | T8: =C8*(1+Assumptions!$B$7)^14*(1-Assumptions!$B$14*14)-D8*Assumptions!$B$23*(1+Assumptions!$B$24)^14 | U8: =NPV(Assumptions!$B$25,F8:T8)+E8 | V8: =IFERROR(IRR(E8:T8),"-")
A9: 100/200 | B9: ='Sizing Comparison'!K9 | C9: ='Sizing Comparison'!H9 | D9: ='Sizing Comparison'!I9 | E9: =-B9 | F9: =C9*(1+Assumptions!$B$7)^0*(1-Assumptions!$B$14*0)-D9*Assumptions!$B$23*(1+Assumptions!$B$24)^0 | G9: =C9*(1+Assumptions!$B$7)^1*(1-Assumptions!$B$14*1)-D9*Assumptions!$B$23*(1+Assumptions!$B$24)^1 | H9: =C9*(1+Assumptions!$B$7)^2*(1-Assumptions!$B$14*2)-D9*Assumptions!$B$23*(1+Assumptions!$B$24)^2 | I9: =C9*(1+Assumptions!$B$7)^3*(1-Assumptions!$B$14*3)-D9*Assumptions!$B$23*(1+Assumptions!$B$24)^3 | J9: =C9*(1+Assumptions!$B$7)^4*(1-Assumptions!$B$14*4)-D9*Assumptions!$B$23*(1+Assumptions!$B$24)^4 | K9: =C9*(1+Assumptions!$B$7)^5*(1-Assumptions!$B$14*5)-D9*Assumptions!$B$23*(1+Assumptions!$B$24)^5 | L9: =C9*(1+Assumptions!$B$7)^6*(1-Assumptions!$B$14*6)-D9*Assumptions!$B$23*(1+Assumptions!$B$24)^6 | M9: =C9*(1+Assumptions!$B$7)^7*(1-Assumptions!$B$14*7)-D9*Assumptions!$B$23*(1+Assumptions!$B$24)^7 | N9: =C9*(1+Assumptions!$B$7)^8*(1-Assumptions!$B$14*8)-D9*Assumptions!$B$23*(1+Assumptions!$B$24)^8 | O9: =C9*(1+Assumptions!$B$7)^9*(1-Assumptions!$B$14*9)-D9*Assumptions!$B$23*(1+Assumptions!$B$24)^9 | P9: =C9*(1+Assumptions!$B$7)^10*(1-Assumptions!$B$14*10)-D9*Assumptions!$B$23*(1+Assumptions!$B$24)^10 | Q9: =C9*(1+Assumptions!$B$7)^11*(1-Assumptions!$B$14*11)-D9*Assumptions!$B$23*(1+Assumptions!$B$24)^11 | R9: =C9*(1+Assumptions!$B$7)^12*(1-Assumptions!$B$14*12)-D9*Assumptions!$B$23*(1+Assumptions!$B$24)^12 | S9: =C9*(1+Assumptions!$B$7)^13*(1-Assumptions!$B$14*13)-D9*Assumptions!$B$23*(1+Assumptions!$B$24)^13 | T9: =C9*(1+Assumptions!$B$7)^14*(1-Assumptions!$B$14*14)-D9*Assumptions!$B$23*(1+Assumptions!$B$24)^14 | U9: =NPV(Assumptions!$B$25,F9:T9)+E9 | V9: =IFERROR(IRR(E9:T9),"-")
A10: 100/300 | B10: ='Sizing Comparison'!K10 | C10: ='Sizing Comparison'!H10 | D10: ='Sizing Comparison'!I10 | E10: =-B10 | F10: =C10*(1+Assumptions!$B$7)^0*(1-Assumptions!$B$14*0)-D10*Assumptions!$B$23*(1+Assumptions!$B$24)^0 | G10: =C10*(1+Assumptions!$B$7)^1*(1-Assumptions!$B$14*1)-D10*Assumptions!$B$23*(1+Assumptions!$B$24)^1 | H10: =C10*(1+Assumptions!$B$7)^2*(1-Assumptions!$B$14*2)-D10*Assumptions!$B$23*(1+Assumptions!$B$24)^2 | I10: =C10*(1+Assumptions!$B$7)^3*(1-Assumptions!$B$14*3)-D10*Assumptions!$B$23*(1+Assumptions!$B$24)^3 | J10: =C10*(1+Assumptions!$B$7)^4*(1-Assumptions!$B$14*4)-D10*Assumptions!$B$23*(1+Assumptions!$B$24)^4 | K10: =C10*(1+Assumptions!$B$7)^5*(1-Assumptions!$B$14*5)-D10*Assumptions!$B$23*(1+Assumptions!$B$24)^5 | L10: =C10*(1+Assumptions!$B$7)^6*(1-Assumptions!$B$14*6)-D10*Assumptions!$B$23*(1+Assumptions!$B$24)^6 | M10: =C10*(1+Assumptions!$B$7)^7*(1-Assumptions!$B$14*7)-D10*Assumptions!$B$23*(1+Assumptions!$B$24)^7 | N10: =C10*(1+Assumptions!$B$7)^8*(1-Assumptions!$B$14*8)-D10*Assumptions!$B$23*(1+Assumptions!$B$24)^8 | O10: =C10*(1+Assumptions!$B$7)^9*(1-Assumptions!$B$14*9)-D10*Assumptions!$B$23*(1+Assumptions!$B$24)^9 | P10: =C10*(1+Assumptions!$B$7)^10*(1-Assumptions!$B$14*10)-D10*Assumptions!$B$23*(1+Assumptions!$B$24)^10 | Q10: =C10*(1+Assumptions!$B$7)^11*(1-Assumptions!$B$14*11)-D10*Assumptions!$B$23*(1+Assumptions!$B$24)^11 | R10: =C10*(1+Assumptions!$B$7)^12*(1-Assumptions!$B$14*12)-D10*Assumptions!$B$23*(1+Assumptions!$B$24)^12 | S10: =C10*(1+Assumptions!$B$7)^13*(1-Assumptions!$B$14*13)-D10*Assumptions!$B$23*(1+Assumptions!$B$24)^13 | T10: =C10*(1+Assumptions!$B$7)^14*(1-Assumptions!$B$14*14)-D10*Assumptions!$B$23*(1+Assumptions!$B$24)^14 | U10: =NPV(Assumptions!$B$25,F10:T10)+E10 | V10: =IFERROR(IRR(E10:T10),"-")
A11: 100/400 | B11: ='Sizing Comparison'!K11 | C11: ='Sizing Comparison'!H11 | D11: ='Sizing Comparison'!I11 | E11: =-B11 | F11: =C11*(1+Assumptions!$B$7)^0*(1-Assumptions!$B$14*0)-D11*Assumptions!$B$23*(1+Assumptions!$B$24)^0 | G11: =C11*(1+Assumptions!$B$7)^1*(1-Assumptions!$B$14*1)-D11*Assumptions!$B$23*(1+Assumptions!$B$24)^1 | H11: =C11*(1+Assumptions!$B$7)^2*(1-Assumptions!$B$14*2)-D11*Assumptions!$B$23*(1+Assumptions!$B$24)^2 | I11: =C11*(1+Assumptions!$B$7)^3*(1-Assumptions!$B$14*3)-D11*Assumptions!$B$23*(1+Assumptions!$B$24)^3 | J11: =C11*(1+Assumptions!$B$7)^4*(1-Assumptions!$B$14*4)-D11*Assumptions!$B$23*(1+Assumptions!$B$24)^4 | K11: =C11*(1+Assumptions!$B$7)^5*(1-Assumptions!$B$14*5)-D11*Assumptions!$B$23*(1+Assumptions!$B$24)^5 | L11: =C11*(1+Assumptions!$B$7)^6*(1-Assumptions!$B$14*6)-D11*Assumptions!$B$23*(1+Assumptions!$B$24)^6 | M11: =C11*(1+Assumptions!$B$7)^7*(1-Assumptions!$B$14*7)-D11*Assumptions!$B$23*(1+Assumptions!$B$24)^7 | N11: =C11*(1+Assumptions!$B$7)^8*(1-Assumptions!$B$14*8)-D11*Assumptions!$B$23*(1+Assumptions!$B$24)^8 | O11: =C11*(1+Assumptions!$B$7)^9*(1-Assumptions!$B$14*9)-D11*Assumptions!$B$23*(1+Assumptions!$B$24)^9 | P11: =C11*(1+Assumptions!$B$7)^10*(1-Assumptions!$B$14*10)-D11*Assumptions!$B$23*(1+Assumptions!$B$24)^10 | Q11: =C11*(1+Assumptions!$B$7)^11*(1-Assumptions!$B$14*11)-D11*Assumptions!$B$23*(1+Assumptions!$B$24)^11 | R11: =C11*(1+Assumptions!$B$7)^12*(1-Assumptions!$B$14*12)-D11*Assumptions!$B$23*(1+Assumptions!$B$24)^12 | S11: =C11*(1+Assumptions!$B$7)^13*(1-Assumptions!$B$14*13)-D11*Assumptions!$B$23*(1+Assumptions!$B$24)^13 | T11: =C11*(1+Assumptions!$B$7)^14*(1-Assumptions!$B$14*14)-D11*Assumptions!$B$23*(1+Assumptions!$B$24)^14 | U11: =NPV(Assumptions!$B$25,F11:T11)+E11 | V11: =IFERROR(IRR(E11:T11),"-")
A12: 150/300 | B12: ='Sizing Comparison'!K12 | C12: ='Sizing Comparison'!H12 | D12: ='Sizing Comparison'!I12 | E12: =-B12 | F12: =C12*(1+Assumptions!$B$7)^0*(1-Assumptions!$B$14*0)-D12*Assumptions!$B$23*(1+Assumptions!$B$24)^0 | G12: =C12*(1+Assumptions!$B$7)^1*(1-Assumptions!$B$14*1)-D12*Assumptions!$B$23*(1+Assumptions!$B$24)^1 | H12: =C12*(1+Assumptions!$B$7)^2*(1-Assumptions!$B$14*2)-D12*Assumptions!$B$23*(1+Assumptions!$B$24)^2 | I12: =C12*(1+Assumptions!$B$7)^3*(1-Assumptions!$B$14*3)-D12*Assumptions!$B$23*(1+Assumptions!$B$24)^3 | J12: =C12*(1+Assumptions!$B$7)^4*(1-Assumptions!$B$14*4)-D12*Assumptions!$B$23*(1+Assumptions!$B$24)^4 | K12: =C12*(1+Assumptions!$B$7)^5*(1-Assumptions!$B$14*5)-D12*Assumptions!$B$23*(1+Assumptions!$B$24)^5 | L12: =C12*(1+Assumptions!$B$7)^6*(1-Assumptions!$B$14*6)-D12*Assumptions!$B$23*(1+Assumptions!$B$24)^6 | M12: =C12*(1+Assumptions!$B$7)^7*(1-Assumptions!$B$14*7)-D12*Assumptions!$B$23*(1+Assumptions!$B$24)^7 | N12: =C12*(1+Assumptions!$B$7)^8*(1-Assumptions!$B$14*8)-D12*Assumptions!$B$23*(1+Assumptions!$B$24)^8 | O12: =C12*(1+Assumptions!$B$7)^9*(1-Assumptions!$B$14*9)-D12*Assumptions!$B$23*(1+Assumptions!$B$24)^9 | P12: =C12*(1+Assumptions!$B$7)^10*(1-Assumptions!$B$14*10)-D12*Assumptions!$B$23*(1+Assumptions!$B$24)^10 | Q12: =C12*(1+Assumptions!$B$7)^11*(1-Assumptions!$B$14*11)-D12*Assumptions!$B$23*(1+Assumptions!$B$24)^11 | R12: =C12*(1+Assumptions!$B$7)^12*(1-Assumptions!$B$14*12)-D12*Assumptions!$B$23*(1+Assumptions!$B$24)^12 | S12: =C12*(1+Assumptions!$B$7)^13*(1-Assumptions!$B$14*13)-D12*Assumptions!$B$23*(1+Assumptions!$B$24)^13 | T12: =C12*(1+Assumptions!$B$7)^14*(1-Assumptions!$B$14*14)-D12*Assumptions!$B$23*(1+Assumptions!$B$24)^14 | U12: =NPV(Assumptions!$B$25,F12:T12)+E12 | V12: =IFERROR(IRR(E12:T12),"-")
A13: 200/400 | B13: ='Sizing Comparison'!K13 | C13: ='Sizing Comparison'!H13 | D13: ='Sizing Comparison'!I13 | E13: =-B13 | F13: =C13*(1+Assumptions!$B$7)^0*(1-Assumptions!$B$14*0)-D13*Assumptions!$B$23*(1+Assumptions!$B$24)^0 | G13: =C13*(1+Assumptions!$B$7)^1*(1-Assumptions!$B$14*1)-D13*Assumptions!$B$23*(1+Assumptions!$B$24)^1 | H13: =C13*(1+Assumptions!$B$7)^2*(1-Assumptions!$B$14*2)-D13*Assumptions!$B$23*(1+Assumptions!$B$24)^2 | I13: =C13*(1+Assumptions!$B$7)^3*(1-Assumptions!$B$14*3)-D13*Assumptions!$B$23*(1+Assumptions!$B$24)^3 | J13: =C13*(1+Assumptions!$B$7)^4*(1-Assumptions!$B$14*4)-D13*Assumptions!$B$23*(1+Assumptions!$B$24)^4 | K13: =C13*(1+Assumptions!$B$7)^5*(1-Assumptions!$B$14*5)-D13*Assumptions!$B$23*(1+Assumptions!$B$24)^5 | L13: =C13*(1+Assumptions!$B$7)^6*(1-Assumptions!$B$14*6)-D13*Assumptions!$B$23*(1+Assumptions!$B$24)^6 | M13: =C13*(1+Assumptions!$B$7)^7*(1-Assumptions!$B$14*7)-D13*Assumptions!$B$23*(1+Assumptions!$B$24)^7 | N13: =C13*(1+Assumptions!$B$7)^8*(1-Assumptions!$B$14*8)-D13*Assumptions!$B$23*(1+Assumptions!$B$24)^8 | O13: =C13*(1+Assumptions!$B$7)^9*(1-Assumptions!$B$14*9)-D13*Assumptions!$B$23*(1+Assumptions!$B$24)^9 | P13: =C13*(1+Assumptions!$B$7)^10*(1-Assumptions!$B$14*10)-D13*Assumptions!$B$23*(1+Assumptions!$B$24)^10 | Q13: =C13*(1+Assumptions!$B$7)^11*(1-Assumptions!$B$14*11)-D13*Assumptions!$B$23*(1+Assumptions!$B$24)^11 | R13: =C13*(1+Assumptions!$B$7)^12*(1-Assumptions!$B$14*12)-D13*Assumptions!$B$23*(1+Assumptions!$B$24)^12 | S13: =C13*(1+Assumptions!$B$7)^13*(1-Assumptions!$B$14*13)-D13*Assumptions!$B$23*(1+Assumptions!$B$24)^13 | T13: =C13*(1+Assumptions!$B$7)^14*(1-Assumptions!$B$14*14)-D13*Assumptions!$B$23*(1+Assumptions!$B$24)^14 | U13: =NPV(Assumptions!$B$25,F13:T13)+E13 | V13: =IFERROR(IRR(E13:T13),"-")

Sheet Load Profile
A1: Load Analysis — Calendar 2025 (representative year)
A3: Annual energy | B3: 224726
A4: Peak demand | B4: 114.9
A5: Average load | B5: 25.7
A6: Load factor | B6: =B5/B4
A9: Month | B9: Energy (kWh) | C9: Peak (kW) | D9: Demand chg $ | E9: Energy chg $ | F9: Total $
A10: Jan | B10: 35978 | C10: 80.9 | D10: =C10*Assumptions!$B$5 | E10: =B10*Assumptions!$B$4 | F10: =D10+E10
A11: Feb | B11: 34421 | C11: 90.6 | D11: =C11*Assumptions!$B$5 | E11: =B11*Assumptions!$B$4 | F11: =D11+E11
A12: Mar | B12: 43051 | C12: 112.4 | D12: =C12*Assumptions!$B$5 | E12: =B12*Assumptions!$B$4 | F12: =D12+E12
A13: Apr | B13: 28133 | C13: 81.2 | D13: =C13*Assumptions!$B$5 | E13: =B13*Assumptions!$B$4 | F13: =D13+E13
A14: May | B14: 6245 | C14: 29.5 | D14: =C14*Assumptions!$B$5 | E14: =B14*Assumptions!$B$4 | F14: =D14+E14
A15: Jun | B15: 4765 | C15: 26.5 | D15: =C15*Assumptions!$B$5 | E15: =B15*Assumptions!$B$4 | F15: =D15+E15
A16: Jul | B16: 4316 | C16: 21.3 | D16: =C16*Assumptions!$B$5 | E16: =B16*Assumptions!$B$4 | F16: =D16+E16
A17: Aug | B17: 3468 | C17: 24 | D17: =C17*Assumptions!$B$5 | E17: =B17*Assumptions!$B$4 | F17: =D17+E17
A18: Sep | B18: 2927 | C18: 16.9 | D18: =C18*Assumptions!$B$5 | E18: =B18*Assumptions!$B$4 | F18: =D18+E18
A19: Oct | B19: 2606 | C19: 18.4 | D19: =C19*Assumptions!$B$5 | E19: =B19*Assumptions!$B$4 | F19: =D19+E19
A20: Nov | B20: 34658 | C20: 114.9 | D20: =C20*Assumptions!$B$5 | E20: =B20*Assumptions!$B$4 | F20: =D20+E20
A21: Dec | B21: 24158 | C21: 70.9 | D21: =C21*Assumptions!$B$5 | E21: =B21*Assumptions!$B$4 | F21: =D21+E21
A22: TOTAL | B22: =SUM(B10:B21) | D22: =SUM(D10:D21) | E22: =SUM(E10:E21) | F22: =SUM(F10:F21)

Sheet Bill Impact
A1: Monthly Bill — Before vs After (50 kW / 150 kWh)
A3: Month | B3: Peak before kW | C3: Peak after kW | D3: kW shaved | E3: Bill before $ | F3: Bill after $ | G3: Savings $
A4: Jan | B4: 80.9 | C4: 54.7 | D4: =B4-C4 | E4: =B4*Assumptions!$B$5+35978*Assumptions!$B$4 | F4: =C4*Assumptions!$B$5+35978*Assumptions!$B$4 | G4: =E4-F4
A5: Feb | B5: 90.6 | C5: 58.5 | D5: =B5-C5 | E5: =B5*Assumptions!$B$5+34421*Assumptions!$B$4 | F5: =C5*Assumptions!$B$5+34421*Assumptions!$B$4 | G5: =E5-F5
A6: Mar | B6: 112.4 | C6: 93.6 | D6: =B6-C6 | E6: =B6*Assumptions!$B$5+43051*Assumptions!$B$4 | F6: =C6*Assumptions!$B$5+43051*Assumptions!$B$4 | G6: =E6-F6
A7: Apr | B7: 81.2 | C7: 64.9 | D7: =B7-C7 | E7: =B7*Assumptions!$B$5+28133*Assumptions!$B$4 | F7: =C7*Assumptions!$B$5+28133*Assumptions!$B$4 | G7: =E7-F7
A8: May | B8: 29.5 | C8: 9.9 | D8: =B8-C8 | E8: =B8*Assumptions!$B$5+6245*Assumptions!$B$4 | F8: =C8*Assumptions!$B$5+6245*Assumptions!$B$4 | G8: =E8-F8
A9: Jun | B9: 26.5 | C9: 11.4 | D9: =B9-C9 | E9: =B9*Assumptions!$B$5+4765*Assumptions!$B$4 | F9: =C9*Assumptions!$B$5+4765*Assumptions!$B$4 | G9: =E9-F9
A10: Jul | B10: 21.3 | C10: 6.3 | D10: =B10-C10 | E10: =B10*Assumptions!$B$5+4316*Assumptions!$B$4 | F10: =C10*Assumptions!$B$5+4316*Assumptions!$B$4 | G10: =E10-F10
A11: Aug | B11: 24 | C11: 5.6 | D11: =B11-C11 | E11: =B11*Assumptions!$B$5+3468*Assumptions!$B$4 | F11: =C11*Assumptions!$B$5+3468*Assumptions!$B$4 | G11: =E11-F11
A12: Sep | B12: 16.9 | C12: 5.3 | D12: =B12-C12 | E12: =B12*Assumptions!$B$5+2927*Assumptions!$B$4 | F12: =C12*Assumptions!$B$5+2927*Assumptions!$B$4 | G12: =E12-F12
A13: Oct | B13: 18.4 | C13: 5.8 | D13: =B13-C13 | E13: =B13*Assumptions!$B$5+2606*Assumptions!$B$4 | F13: =C13*Assumptions!$B$5+2606*Assumptions!$B$4 | G13: =E13-F13
A14: Nov | B14: 114.9 | C14: 90 | D14: =B14-C14 | E14: =B14*Assumptions!$B$5+34658*Assumptions!$B$4 | F14: =C14*Assumptions!$B$5+34658*Assumptions!$B$4 | G14: =E14-F14
A15: Dec | B15: 70.9 | C15: 42.9 | D15: =B15-C15 | E15: =B15*Assumptions!$B$5+24158*Assumptions!$B$4 | F15: =C15*Assumptions!$B$5+24158*Assumptions!$B$4 | G15: =E15-F15
A16: TOTAL | E16: =SUM(E4:E15) | F16: =SUM(F4:F15) | G16: =SUM(G4:G15)

Sheet Dispatch
A1: What the Battery Does — cold week Mar 2025 (100 kW/300 kWh, ceiling ~80.9 kW)
A3: Hour | B3: Load kW | C3: Net grid kW | D3: SOC kWh
A4: Mon 00:00 | B4: 47.4 | C4: 47.4 | D4: 300
A5: Mon 01:00 | B5: 48.1 | C5: 48.1 | D5: 300
A6: Mon 02:00 | B6: 47.8 | C6: 47.8 | D6: 300
A7: Mon 03:00 | B7: 47.8 | C7: 47.8 | D7: 300
A8: Mon 04:00 | B8: 29.9 | C8: 29.9 | D8: 300
A9: Mon 05:00 | B9: 29.2 | C9: 29.2 | D9: 300
A10: Mon 06:00 | B10: 29.5 | C10: 29.5 | D10: 300
A11: Mon 07:00 | B11: 36.9 | C11: 36.9 | D11: 300
A12: Mon 08:00 | B12: 45.9 | C12: 45.9 | D12: 300
A13: Mon 09:00 | B13: 46 | C13: 46 | D13: 300
A14: Mon 10:00 | B14: 45.3 | C14: 45.3 | D14: 300
A15: Mon 11:00 | B15: 48 | C15: 48 | D15: 300
... A171: Sun 23:00 | B171: 76.5 | C171: 76.5 | D171: 300

Sheet Cash Flow
A1: 15-Year Cash Flow — pulls live from CF_Calc
A2: These two sizes mirror the CF_Calc engine. Change Assumptions and they move.
A4: Value pick: 50/150 | E4: Deep shave: 100/300
A5: Year | B5: Net cash flow $ | C5: Cumulative $ | E5: Year | F5: Net cash flow $ | G5: Cumulative $
A6: 0 | B6: ='CF_Calc'!E7 | C6: =B6 | E6: 0 | F6: ='CF_Calc'!E10 | G6: =F6
A7: 1 | B7: ='CF_Calc'!F7 | C7: =C6+B7 | E7: 1 | F7: ='CF_Calc'!F10 | G7: =G6+F7
A8: 2 | B8: ='CF_Calc'!G7 | C8: =C7+B8 | E8: 2 | F8: ='CF_Calc'!G10 | G8: =G7+F8
A9: 3 | B9: ='CF_Calc'!H7 | C9: =C8+B9 | E9: 3 | F9: ='CF_Calc'!H10 | G9: =G8+F9
A10: 4 | B10: ='CF_Calc'!I7 | C10: =C9+B10 | E10: 4 | F10: ='CF_Calc'!I10 | G10: =G9+F10
A11: 5 | B11: ='CF_Calc'!J7 | C11: =C10+B11 | E11: 5 | F11: ='CF_Calc'!J10 | G11: =G10+F11
A12: 6 | B12: ='CF_Calc'!K7 | C12: =C11+B12 | E12: 6 | F12: ='CF_Calc'!K10 | G12: =G11+F12
A13: 7 | B13: ='CF_Calc'!L7 | C13: =C12+B13 | E13: 7 | F13: ='CF_Calc'!L10 | G13: =G12+F13
A14: 8 | B14: ='CF_Calc'!M7 | C14: =C13+B14 | E14: 8 | F14: ='CF_Calc'!M10 | G14: =G13+F14
A15: 9 | B15: ='CF_Calc'!N7 | C15: =C14+B15 | E15: 9 | F15: ='CF_Calc'!N10 | G15: =G14+F15
A16: 10 | B16: ='CF_Calc'!O7 | C16: =C15+B16 | E16: 10 | F16: ='CF_Calc'!O10 | G16: =G15+F16
A17: 11 | B17: ='CF_Calc'!P7 | C17: =C16+B17 | E17: 11 | F17: ='CF_Calc'!P10 | G17: =G16+F17
A18: 12 | B18: ='CF_Calc'!Q7 | C18: =C17+B18 | E18: 12 | F18: ='CF_Calc'!Q10 | G18: =G17+F18
A19: 13 | B19: ='CF_Calc'!R7 | C19: =C18+B19 | E19: 13 | F19: ='CF_Calc'!R10 | G19: =G18+F19
A20: 14 | B20: ='CF_Calc'!S7 | C20: =C19+B20 | E20: 14 | F20: ='CF_Calc'!S10 | G20: =G19+F20
A21: 15 | B21: ='CF_Calc'!T7 | C21: =C20+B21 | E21: 15 | F21: ='CF_Calc'!T10 | G21: =G20+F21
A23: Payback (yr) | B23: ='Sizing Comparison'!L7 | E23: Payback (yr) | F23: ='Sizing Comparison'!L10
A24: NPV | B24: ='CF_Calc'!U7 | E24: NPV | F24: ='CF_Calc'!U10
A25: IRR | B25: ='CF_Calc'!V7 | E25: IRR | F25: ='CF_Calc'!V10

Sheet Backup Resilience
A1: Backup / Resilience — outage runtime (hours)
A2: Usable = Energy × DoD (Assumptions!B13). Runtime = usable ÷ load served.
A4: Energy kWh | B4: Usable kWh | C4: Winter ~48 kW | D4: Shoulder ~25 kW | E4: Summer ~5 kW | F4: Critical ~10 kW
A5: 60 | B5: =A5*Assumptions!$B$13 | C5: =B5/48 | D5: =B5/25 | E5: =B5/5 | F5: =B5/10
A6: 100 | B6: =A6*Assumptions!$B$13 | C6: =B6/48 | D6: =B6/25 | E6: =B6/5 | F6: =B6/10
A7: 150 | B7: =A7*Assumptions!$B$13 | C7: =B7/48 | D7: =B7/25 | E7: =B7/5 | F7: =B7/10
A8: 200 | B8: =A8*Assumptions!$B$13 | C8: =B8/48 | D8: =B8/25 | E8: =B8/5 | F8: =B8/10
A9: 300 | B9: =A9*Assumptions!$B$13 | C9: =B9/48 | D9: =B9/25 | E9: =B9/5 | F9: =B9/10
A10: 400 | B10: =A10*Assumptions!$B$13 | C10: =B10/48 | D10: =B10/25 | E10: =B10/5 | F10: =B10/10

Sheet Sensitivity
A1: Sensitivity — Payback (yrs) of 50/150 vs demand charge & battery cost
A2: Responds to the ITC assumption. Net capex=150×$/kWh×(1−ITC); savings=238.7×demand-rate.
A4: Demand $/kW ↓ / Battery $/kWh → | B4: 400 | C4: 500 | D4: 600 | E4: 700 | F4: 800
A5: 10 | B5: =(150*400*(1-Assumptions!$B$20))/(238.7*10) | C5: =(150*500*(1-Assumptions!$B$20))/(238.7*10) | D5: =(150*600*(1-Assumptions!$B$20))/(238.7*10) | E5: =(150*700*(1-Assumptions!$B$20))/(238.7*10) | F5: =(150*800*(1-Assumptions!$B$20))/(238.7*10)
A6: 15 | B6: =(150*400*(1-Assumptions!$B$20))/(238.7*15) | C6: =(150*500*(1-Assumptions!$B$20))/(238.7*15) | D6: =(150*600*(1-Assumptions!$B$20))/(238.7*15) | E6: =(150*700*(1-Assumptions!$B$20))/(238.7*15) | F6: =(150*800*(1-Assumptions!$B$20))/(238.7*15)
A7: 20 | B7: =(150*400*(1-Assumptions!$B$20))/(238.7*20) | C7: =(150*500*(1-Assumptions!$B$20))/(238.7*20) | D7: =(150*600*(1-Assumptions!$B$20))/(238.7*20) | E7: =(150*700*(1-Assumptions!$B$20))/(238.7*20) | F7: =(150*800*(1-Assumptions!$B$20))/(238.7*20)
A8: 25.84 | B8: =(150*400*(1-Assumptions!$B$20))/(238.7*25.84) | C8: =(150*500*(1-Assumptions!$B$20))/(238.7*25.84) | D8: =(150*600*(1-Assumptions!$B$20))/(238.7*25.84) | E8: =(150*700*(1-Assumptions!$B$20))/(238.7*25.84) | F8: =(150*800*(1-Assumptions!$B$20))/(238.7*25.84)
A9: 30 | B9: =(150*400*(1-Assumptions!$B$20))/(238.7*30) | C9: =(150*500*(1-Assumptions!$B$20))/(238.7*30) | D9: =(150*600*(1-Assumptions!$B$20))/(238.7*30) | E9: =(150*700*(1-Assumptions!$B$20))/(238.7*30) | F9: =(150*800*(1-Assumptions!$B$20))/(238.7*30)
A10: 40 | B10: =(150*400*(1-Assumptions!$B$20))/(238.7*40) | C10: =(150*500*(1-Assumptions!$B$20))/(238.7*40) | D10: =(150*600*(1-Assumptions!$B$20))/(238.7*40) | E10: =(150*700*(1-Assumptions!$B$20))/(238.7*40) | F10: =(150*800*(1-Assumptions!$B$20))/(238.7*40)
A12: Cells = simple payback in years. Lower is better.
